codeql_wrapper/__init__.py
codeql_wrapper/__main__.py
codeql_wrapper/domain/__init__.py
codeql_wrapper/domain/entities/__init__.py
codeql_wrapper/domain/entities/codeql_analysis.py
codeql_wrapper/domain/use_cases/__init__.py
codeql_wrapper/domain/use_cases/codeql_analysis_use_case.py
codeql_wrapper/domain/use_cases/sarif_upload_use_case.py
codeql_wrapper/entrypoints/__init__.py
codeql_wrapper/entrypoints/cli/__init__.py
codeql_wrapper/entrypoints/cli/analyze.py
codeql_wrapper/entrypoints/cli/cli.py
codeql_wrapper/entrypoints/cli/install.py
codeql_wrapper/infrastructure/__init__.py
codeql_wrapper/infrastructure/codeql_installer.py
codeql_wrapper/infrastructure/codeql_runner.py
codeql_wrapper/infrastructure/directory_manager.py
codeql_wrapper/infrastructure/git_utils.py
codeql_wrapper/infrastructure/language_detector.py
codeql_wrapper/infrastructure/logger.py
codeql_wrapper/infrastructure/system_resource_manager.py
codeql_wrapper-0.1.13.dist-info/LICENSE
codeql_wrapper-0.1.13.dist-info/METADATA
codeql_wrapper-0.1.13.dist-info/WHEEL
codeql_wrapper-0.1.13.dist-info/entry_points.txt
codeql_wrapper-0.1.13.dist-info/RECORD
