Metadata-Version: 2.1
Name: codeql-wrapper
Version: 0.1.13
Summary: A universal Python CLI wrapper for running CodeQL analysis on any type of project (monorepo or single repository) across different CI/CD platforms including Jenkins, GitHub Actions, Harness, and any environment where Python scripts can be executed.
Home-page: https://github.com/yourusername/codeql-wrapper
License: MIT
Keywords: codeql,monorepo
Author: Mateus Perdigão Domiciano
Author-email: mateus.domiciano@moduscreate.com
Requires-Python: >=3.9,<4.0
Classifier: Development Status :: 4 - Beta
Classifier: Intended Audience :: Developers
Classifier: License :: OSI Approved :: MIT License
Classifier: Operating System :: OS Independent
Classifier: Programming Language :: Python :: 3
Classifier: Programming Language :: Python :: 3.9
Classifier: Programming Language :: Python :: 3.10
Classifier: Programming Language :: Python :: 3.11
Classifier: Programming Language :: Python :: 3.12
Classifier: Programming Language :: Python :: 3.13
Requires-Dist: click (>=8.0.0,<9.0.0)
Requires-Dist: colorama (>=0.4.6,<0.5.0)
Requires-Dist: gitpython (>=3.1.44,<4.0.0)
Requires-Dist: psutil (>=5.8.0,<6.0.0)
Project-URL: Documentation, https://github.com/yourusername/codeql-wrapper
Project-URL: Repository, https://github.com/yourusername/codeql-wrapper
